autogoal_wikipedia/__init__.py
autogoal_wikipedia/_base.py
autogoal_wikipedia-0.8.4.dist-info/WHEEL
autogoal_wikipedia-0.8.4.dist-info/METADATA
autogoal_wikipedia-0.8.4.dist-info/RECORD
